atpdataset/__init__.py
atpdataset/c_py.py
atpdataset/csv.py
atpdataset/csv_object.py
atpdataset/dataset.py
atpdataset/dictionary.py
atpdataset/records.py
atpdataset/utils.py
atpdataset/io/__init__.py
atpdataset/io/aio.py
atpdataset/io/io.py
atpdataset-0.0.10.dist-info/LICENSE
atpdataset-0.0.10.dist-info/METADATA
atpdataset-0.0.10.dist-info/WHEEL
atpdataset-0.0.10.dist-info/entry_points.txt
atpdataset-0.0.10.dist-info/top_level.txt
atpdataset-0.0.10.dist-info/RECORD
